LICENSE
README.md
pyproject.toml
setup.py
dameopencv/LICENSE
dameopencv/damebilateralfilt.py
dameopencv/damecat.py
dameopencv/damecvresizing.py
dameopencv/damedetectcolors.py
dameopencv/damedetectcontours.py
dameopencv/damedetectcorner.py
dameopencv/damedetectobject.py
dameopencv/damedisplayimage.py
dameopencv/damefourier.py
dameopencv/damegrayscaling.py
dameopencv/damehdri.py
dameopencv/damelaplace.py
dameopencv/damemaksoperations.py
dameopencv/runtests.sh
dameopencv.egg-info/PKG-INFO
dameopencv.egg-info/SOURCES.txt
dameopencv.egg-info/dependency_links.txt
dameopencv.egg-info/entry_points.txt
dameopencv.egg-info/not-zip-safe
dameopencv.egg-info/requires.txt
dameopencv.egg-info/top_level.txt
dameopencv/files/img/528px-Arnold_Schwarzenegger.jpg
dameopencv/files/img/Afghan_girl_Pashtun.jpg
dameopencv/files/img/RGB.jpg
dameopencv/files/img/RGB.png
dameopencv/files/img/Tischbank.jpg
dameopencv/files/img/arnie.jpg
dameopencv/files/img/cat_damaged.png
dameopencv/files/img/cat_inpainted.png
dameopencv/files/img/cat_mask.png
dameopencv/files/img/circle.jpg
dameopencv/files/img/davidamobelisco.jpg
dameopencv/files/img/gaby.jpg
dameopencv/files/img/girl1.jpg
dameopencv/files/img/girl2.jpg
dameopencv/files/img/kid1.jpg
dameopencv/files/img/kid2.jpg
dameopencv/files/img/man1.jpg
dameopencv/files/img/man2.jpg
dameopencv/files/img/maria.jpg
dameopencv/files/img/rgb.png
dameopencv/files/img/square.jpg
dameopencv/files/img/stop.jpg
dameopencv/files/img/woman1.jpg
dameopencv/tests/__init__.py
dameopencv/tests/test_basics.py